aiokubernetes/__init__.py
aiokubernetes/api_client.py
aiokubernetes/api_client_test.py
aiokubernetes/api_proxy.py
aiokubernetes/api_proxy_test.py
aiokubernetes/clients.py
aiokubernetes/configuration.py
aiokubernetes/rest.py
aiokubernetes/swagger.py
aiokubernetes/swagger_test.py
aiokubernetes/utils.py
aiokubernetes/watch.py
aiokubernetes/api/__init__.py
aiokubernetes/api/admissionregistration_api.py
aiokubernetes/api/admissionregistration_v1alpha1_api.py
aiokubernetes/api/admissionregistration_v1beta1_api.py
aiokubernetes/api/apiextensions_api.py
aiokubernetes/api/apiextensions_v1beta1_api.py
aiokubernetes/api/apiregistration_api.py
aiokubernetes/api/apiregistration_v1_api.py
aiokubernetes/api/apiregistration_v1beta1_api.py
aiokubernetes/api/apis_api.py
aiokubernetes/api/apps_api.py
aiokubernetes/api/apps_v1_api.py
aiokubernetes/api/apps_v1beta1_api.py
aiokubernetes/api/apps_v1beta2_api.py
aiokubernetes/api/authentication_api.py
aiokubernetes/api/authentication_v1_api.py
aiokubernetes/api/authentication_v1beta1_api.py
aiokubernetes/api/authorization_api.py
aiokubernetes/api/authorization_v1_api.py
aiokubernetes/api/authorization_v1beta1_api.py
aiokubernetes/api/autoscaling_api.py
aiokubernetes/api/autoscaling_v1_api.py
aiokubernetes/api/autoscaling_v2beta1_api.py
aiokubernetes/api/batch_api.py
aiokubernetes/api/batch_v1_api.py
aiokubernetes/api/batch_v1beta1_api.py
aiokubernetes/api/batch_v2alpha1_api.py
aiokubernetes/api/certificates_api.py
aiokubernetes/api/certificates_v1beta1_api.py
aiokubernetes/api/core_api.py
aiokubernetes/api/core_v1_api.py
aiokubernetes/api/custom_objects_api.py
aiokubernetes/api/events_api.py
aiokubernetes/api/events_v1beta1_api.py
aiokubernetes/api/extensions_api.py
aiokubernetes/api/extensions_v1beta1_api.py
aiokubernetes/api/logs_api.py
aiokubernetes/api/networking_api.py
aiokubernetes/api/networking_v1_api.py
aiokubernetes/api/policy_api.py
aiokubernetes/api/policy_v1beta1_api.py
aiokubernetes-0.6.dist-info/METADATA
aiokubernetes-0.6.dist-info/RECORD
aiokubernetes-0.6.dist-info/WHEEL
aiokubernetes-0.6.dist-info/top_level.txt
