Metadata-Version: 2.1
Name: aiokubernetes
Version: 0.6
Summary: Asynchronous Kubernetes client
Home-page: https://github.com/olitheolix/aiokubernetes
Author: Kubernetes
Author-email: UNKNOWN
License: Apache License Version 2.0
Keywords: Swagger,OpenAPI,Kubernetes,async,asyncio
Platform: UNKNOWN
Classifier: Development Status :: 4 - Beta
Classifier: Topic :: Utilities
Classifier: Intended Audience :: Developers
Classifier: Intended Audience :: Information Technology
Classifier: License :: OSI Approved :: Apache Software License
Classifier: Operating System :: OS Independent
Classifier: Programming Language :: Python
Classifier: Programming Language :: Python :: 3
Classifier: Programming Language :: Python :: 3.6
Classifier: Programming Language :: Python :: 3.7
Requires-Dist: aiohttp
Requires-Dist: certifi (>=14.05.14)
Requires-Dist: google-auth (>=1.0.1)
Requires-Dist: ipython
Requires-Dist: oauthlib
Requires-Dist: python-dateutil (>=2.5.3)
Requires-Dist: pyyaml
Requires-Dist: requests
Requires-Dist: requests-oauthlib
Requires-Dist: setuptools
Requires-Dist: urllib3
